video_generation/base.py
video_generation/example.py
video_generation/factory.py
video_generation/providers/__init__.py
video_generation/providers/luma.py
video_generation/providers/pixverse.py
video_generation/providers/runway.py
video_generation/providers/siliconflow.py
video_generation/providers/stability.py
video_generation/providers/tongyi.py
video_generation/providers/vidu.py
video_generation/providers/zhipu.py
video_generation/size_adapter.py
ai_video_api-0.1.0.dist-info/METADATA
ai_video_api-0.1.0.dist-info/WHEEL
ai_video_api-0.1.0.dist-info/RECORD
